addMath23/__init__.py
addMath23/math_ai23.py
subMath23/__init__.py
subMath23/sub_ai23.py
wheelTest_ai23-0.1.10.dist-info/LICENSE
wheelTest_ai23-0.1.10.dist-info/METADATA
wheelTest_ai23-0.1.10.dist-info/WHEEL
wheelTest_ai23-0.1.10.dist-info/top_level.txt
wheelTest_ai23-0.1.10.dist-info/RECORD
