Metadata-Version: 2.2
Name: wheelTest_ai23
Version: 0.1.10
Summary: 一个简单的数学运算库
Author: Your Name
Classifier: Programming Language :: Python :: 3
Classifier: License :: OSI Approved :: MIT License
Classifier: Operating System :: OS Independent
Requires-Python: >=3.6
License-File: LICENSE
Dynamic: author
Dynamic: classifier
Dynamic: requires-python
Dynamic: summary
